LICENSE
README.md
setup.py
knify/__init__.py
knify/cron_parser.py
knify/curlutil.py
knify/dateutil.py
knify/excelutil.py
knify/fileutil.py
knify/help.py
knify/listutil.py
knify/logger.py
knify/objutil.py
knify/scheduler.py
knify/sqlutil.py
knify/threadutil.py
knify/warnutil.py
knify.egg-info/PKG-INFO
knify.egg-info/SOURCES.txt
knify.egg-info/dependency_links.txt
knify.egg-info/requires.txt
knify.egg-info/top_level.txt
knify/apscheduler/__init__.py
knify/apscheduler/events.py
knify/apscheduler/job.py
knify/apscheduler/util.py
knify/apscheduler/executors/__init__.py
knify/apscheduler/executors/asyncio.py
knify/apscheduler/executors/base.py
knify/apscheduler/executors/debug.py
knify/apscheduler/executors/gevent.py
knify/apscheduler/executors/pool.py
knify/apscheduler/executors/tornado.py
knify/apscheduler/executors/twisted.py
knify/apscheduler/jobstores/__init__.py
knify/apscheduler/jobstores/base.py
knify/apscheduler/jobstores/etcd.py
knify/apscheduler/jobstores/memory.py
knify/apscheduler/jobstores/mongodb.py
knify/apscheduler/jobstores/redis.py
knify/apscheduler/jobstores/rethinkdb.py
knify/apscheduler/jobstores/sqlalchemy.py
knify/apscheduler/jobstores/zookeeper.py
knify/apscheduler/schedulers/__init__.py
knify/apscheduler/schedulers/asyncio.py
knify/apscheduler/schedulers/background.py
knify/apscheduler/schedulers/base.py
knify/apscheduler/schedulers/blocking.py
knify/apscheduler/schedulers/gevent.py
knify/apscheduler/schedulers/qt.py
knify/apscheduler/schedulers/tornado.py
knify/apscheduler/schedulers/twisted.py
knify/apscheduler/triggers/__init__.py
knify/apscheduler/triggers/base.py
knify/apscheduler/triggers/calendarinterval.py
knify/apscheduler/triggers/combining.py
knify/apscheduler/triggers/date.py
knify/apscheduler/triggers/interval.py
knify/apscheduler/triggers/cron/__init__.py
knify/apscheduler/triggers/cron/expressions.py
knify/apscheduler/triggers/cron/fields.py