Metadata-Version: 2.4
Name: knify
Version: 1.9.45
Summary: Development tools for python
Home-page: https://github.com/qicongsheng/knify
Author: qicongsheng
Author-email: qicongsheng@outlook.com
License: MIT License
Keywords: knify
Platform: any
License-File: LICENSE
Requires-Dist: loguru
Requires-Dist: urllib3
Requires-Dist: openpyxl
Requires-Dist: pytz
Requires-Dist: requests
Requires-Dist: curlify
Requires-Dist: uncurl
Requires-Dist: xlrd
Dynamic: author
Dynamic: author-email
Dynamic: home-page
Dynamic: keywords
Dynamic: license
Dynamic: license-file
Dynamic: platform
Dynamic: requires-dist
Dynamic: summary
